initpyproj.py
initpyproj_templates/[template]CHANGELOG
initpyproj_templates/[template]LICENSE
initpyproj_templates/[template]MANIFEST
initpyproj_templates/[template]README
initpyproj_templates/[template]gitignore
initpyproj_templates/[template]setup
initpyproj-1.0.2.dist-info/LICENSE
initpyproj-1.0.2.dist-info/METADATA
initpyproj-1.0.2.dist-info/WHEEL
initpyproj-1.0.2.dist-info/top_level.txt
initpyproj-1.0.2.dist-info/RECORD
